{
	"afrikaans":			{"code":"af",	"mc": "af_za"},
	"albanian":				{"code":"sq",	"mc": "sq_al"},
	"arabic":				{"code":"ar",	"mc": "ar_sa"},
	"azerbaijani":			{"code":"az",	"mc": "az_az"},
	"basque":				{"code":"eu",	"mc": "eu_es"},
	"belarusian":			{"code":"be",	"mc": "be_by"},
	"bulgarian":			{"code":"bg",	"mc": "bg_bg"},
	"catalan":				{"code":"ca",	"mc": "ca_es"},
	"chinesesimplified":	{"code":"zh-CN","mc": "zh_cn"},
	"chinesetraditional":	{"code":"zh-TW","mc": "zh_hk"},
	"croatian":				{"code":"hr",	"mc": "hr_hr"},
	"czech":				{"code":"cs",	"mc": "cs_cz"},
	"danish":				{"code":"da",	"mc": "da_dk"},
	"dutch":				{"code":"nl",	"mc": "nl_nl"},
	"english":				{"code":"en",	"mc": "en_us"},
	"esperanto":			{"code":"eo",	"mc": "eo_uy"},
	"estonian":				{"code":"et",	"mc": "et_ee"},
	"filipino":				{"code":"tl",	"mc": "fil_ph"},
	"finnish":				{"code":"fi",	"mc": "fi_fi"},
	"french":				{"code":"fr",	"mc": "fr_fr"},
	"galician":				{"code":"gl",	"mc": "gl_es"},
	"georgian":				{"code":"ka",	"mc": "ka_ge"},
	"german":				{"code":"de",	"mc": "de_de"},
	"greek":				{"code":"el",	"mc": "el_gr"},
	"hebrew":				{"code":"iw",	"mc": "he_il"},
	"hindi":				{"code":"hi",	"mc": "hi_in"},
	"hungarian":			{"code":"hu",	"mc": "hu_hu"},
	"icelandic":			{"code":"is",	"mc": "is_is"},
	"indonesian":			{"code":"id",	"mc": "id_id"},
	"irish":				{"code":"ga",	"mc": "ga_ie"},
	"italian":				{"code":"it",	"mc": "it_it"},
	"japanese":				{"code":"ja",	"mc": "ja_jp"},
	"kannada":				{"code":"kn",	"mc": "kn_in"},
	"korean":				{"code":"ko",	"mc": "ko_kr"},
	"latin":				{"code":"la",	"mc": "la_la"},
	"latvian":				{"code":"lv",	"mc": "lv_lv"},
	"lithuanian":			{"code":"lt",	"mc": "lt_lt"},
	"macedonian":			{"code":"mk",	"mc": "mk_mk"},
	"malay":				{"code":"ms",	"mc": "ms_my"},
	"maltese":				{"code":"mt",	"mc": "mt_mt"},
	"norwegian":			{"code":"no",	"mc": "nn_no"},
	"persian":				{"code":"fa",	"mc": "fa_ir"},
	"polish":				{"code":"pl",	"mc": "pl_pl"},
	"portuguese":			{"code":"pt",	"mc": "pt_pt"},
	"romanian":				{"code":"ro",	"mc": "ro_ro"},
	"russian":				{"code":"ru",	"mc": "ru_ru"},
	"serbian":				{"code":"sr",	"mc": "sr_sp"},
	"slovak":				{"code":"sk",	"mc": "sk_sk"},
	"slovenian":			{"code":"sl",	"mc": "sl_si"},
	"spanish":				{"code":"es",	"mc": "es_es"},
	"swedish":				{"code":"sv",	"mc": "sv_se"},
	"tamil":				{"code":"ta",	"mc": "ta_in"},
	"thai":					{"code":"th",	"mc": "th_th"},
	"turkish":				{"code":"tr",	"mc": "tr_tr"},
	"ukrainian":			{"code":"uk",	"mc": "uk_ua"},
	"vietnamese":			{"code":"vi",	"mc": "vi_vn"},
	"welsh":				{"code":"cy",	"mc": "cy_gb"},
	"yiddish":				{"code":"yi",	"mc": "yi_de"}
}